concurrent_tasks/__init__.py
concurrent_tasks/background.py
concurrent_tasks/debounce.py
concurrent_tasks/exception_handler.py
concurrent_tasks/periodic.py
concurrent_tasks/pool.py
concurrent_tasks/py.typed
concurrent_tasks/restartable.py
concurrent_tasks/stream.py
concurrent_tasks/thread_safe_pool.py
concurrent_tasks/threaded_pool/__init__.py
concurrent_tasks/threaded_pool/aio.py
concurrent_tasks/threaded_pool/base.py
concurrent_tasks/threaded_pool/blocking.py
concurrent_tasks-1.16.3.dist-info/licenses/LICENSE
concurrent_tasks-1.16.3.dist-info/WHEEL
concurrent_tasks-1.16.3.dist-info/METADATA
concurrent_tasks-1.16.3.dist-info/RECORD
