Metadata-Version: 2.4
Name: concurrent-tasks
Version: 1.16.3
Summary: Tools to run asyncio tasks concurrently.
Author: Gabriel Pajot
Author-email: Gabriel Pajot <gab@lescactus.eu>
License-Expression: MIT
License-File: LICENSE
Requires-Dist: typing-extensions>=4.10
Requires-Python: >=3.9
Project-URL: repository, https://github.com/gpajot/asyncio-concurrent-tasks
